{"series": [{"data": [{"x": "bike", "y": 0.65}, {"x": "bus", "y": 3.89}, {"x": "car", "y": 1.04}, {"x": "drivable area", "y": 8.94}, {"x": "lane", "y": 0.48}, {"x": "motor", "y": 0.84}, {"x": "person", "y": 0.33}, {"x": "rider", "y": 0.69}, {"x": "traffic light", "y": 0.06}, {"x": "traffic sign", "y": 0.14}, {"x": "train", "y": 4.13}, {"x": "truck", "y": 3.03}]}], "options": {"chart": {"type": "treemap", "height": 510}, "legend": {"show": false}, "plotOptions": {"treemap": {"distributed": true, "enableShades": false}}, "title": {"text": "Average area of class objects on image", "align": "left"}, "colors": ["#8a0f51", "#578a0f", "#428a0f", "#8a590f", "#450f8a", "#0f348a", "#0f8a37", "#2e0f8a", "#8a0f12", "#0f678a", "#8a740f", "#7d0f8a"], "tooltip": {"y": {}}}, "type": "treemap", "height": 350, "sly_options": {"tooltip": "Average area of class objects on image is {y}%"}}